<?xml version="1.0" encoding="UTF-8" standalone="no"?><profile><portfolio name="test"><transaction><service/><ticker>GOOG</ticker><shares>10.0</shares><date>2024-05-20</date><service>Purchase</service></transaction><transactions><trans><ticker>GOOG</ticker><share>5.0</share><date>2024-05-20</date><service>Sale</service></trans><trans><ticker>GOOG</ticker><share>5.0</share><date>2024-05-20</date><service>Sale</service></trans><trans><ticker>GOOG</ticker><share>5.0</share><date>2024-05-20</date><service>Sale</service></trans><trans><ticker>GOOG</ticker><share>5.0</share><date>2024-05-20</date><service>Sale</service></trans><trans><ticker>AAPL</ticker><share>50.0</share><date>2024-06-03</date><service>Purchase</service></trans><trans><ticker>GOOG</ticker><share>10.0</share><date>2024-05-20</date><service>Sale</service></trans><trans><ticker>GOOG</ticker><share>5.0</share><date>2024-05-20</date><service>Sale</service></trans></transactions></portfolio><portfolio name="test"><transaction><service/><ticker>GOOG</ticker><shares>10.0</shares><date>2024-05-20</date><service>Purchase</service></transaction><transactions><trans><ticker>GOOG</ticker><share>5.0</share><date>2024-05-20</date><service>Sale</service></trans><trans><ticker>GOOG</ticker><share>5.0</share><date>2024-05-20</date><service>Sale</service></trans><trans><ticker>GOOG</ticker><share>5.0</share><date>2024-05-20</date><service>Sale</service></trans><trans><ticker>GOOG</ticker><share>5.0</share><date>2024-05-20</date><service>Sale</service></trans><trans><ticker>GOOG</ticker><share>10.0</share><date>2024-05-20</date><service>Sale</service></trans><trans><ticker>GOOG</ticker><share>5.0</share><date>2024-05-20</date><service>Sale</service></trans></transactions></portfolio><portfolio name="test"><transaction><service/><ticker>GOOG</ticker><shares>10.0</shares><date>2024-05-20</date><service>Purchase</service></transaction><transactions><trans><ticker>GOOG</ticker><share>5.0</share><date>2024-05-20</date><service>Sale</service></trans><trans><ticker>GOOG</ticker><share>5.0</share><date>2024-05-20</date><service>Sale</service></trans><trans><ticker>GOOG</ticker><share>5.0</share><date>2024-05-20</date><service>Sale</service></trans><trans><ticker>GOOG</ticker><share>5.0</share><date>2024-05-20</date><service>Sale</service></trans><trans><ticker>GOOG</ticker><share>10.0</share><date>2024-05-20</date><service>Sale</service></trans><trans><ticker>GOOG</ticker><share>5.0</share><date>2024-05-20</date><service>Sale</service></trans></transactions></portfolio><portfolio name="test"><transaction><service/><ticker>GOOG</ticker><shares>10.0</shares><date>2024-05-20</date><service>Purchase</service></transaction><transactions><trans><ticker>GOOG</ticker><share>5.0</share><date>2024-05-20</date><service>Sale</service></trans><trans><ticker>GOOG</ticker><share>5.0</share><date>2024-05-20</date><service>Sale</service></trans><trans><ticker>GOOG</ticker><share>5.0</share><date>2024-05-20</date><service>Sale</service></trans><trans><ticker>GOOG</ticker><share>10.0</share><date>2024-05-20</date><service>Sale</service></trans><trans><ticker>GOOG</ticker><share>5.0</share><date>2024-05-20</date><service>Sale</service></trans></transactions></portfolio><portfolio name="test"><transaction><service/><ticker>GOOG</ticker><shares>10.0</shares><date>2024-05-20</date><service>Purchase</service></transaction><transactions><trans><ticker>GOOG</ticker><share>5.0</share><date>2024-05-20</date><service>Sale</service></trans><trans><ticker>GOOG</ticker><share>5.0</share><date>2024-05-20</date><service>Sale</service></trans><trans><ticker>GOOG</ticker><share>10.0</share><date>2024-05-20</date><service>Sale</service></trans><trans><ticker>GOOG</ticker><share>5.0</share><date>2024-05-20</date><service>Sale</service></trans></transactions></portfolio><portfolio name="test"><transaction><service/><ticker>GOOG</ticker><shares>10.0</shares><date>2024-05-20</date><service>Purchase</service></transaction><transactions><trans><ticker>GOOG</ticker><share>5.0</share><date>2024-05-20</date><service>Sale</service></trans><trans><ticker>GOOG</ticker><share>10.0</share><date>2024-05-20</date><service>Sale</service></trans><trans><ticker>GOOG</ticker><share>5.0</share><date>2024-05-20</date><service>Sale</service></trans></transactions></portfolio><portfolio name="test"><transaction><service/><ticker>GOOG</ticker><shares>10.0</shares><date>2024-05-20</date><service>Purchase</service></transaction><transactions><trans><ticker>GOOG</ticker><share>10.0</share><date>2024-05-20</date><service>Sale</service></trans><trans><ticker>GOOG</ticker><share>5.0</share><date>2024-05-20</date><service>Sale</service></trans></transactions></portfolio><portfolio name="test"><stock><ticker>goog</ticker><date>2024-05-20</date><shares>10.0</shares></stock><transaction><service/><ticker>goog</ticker><shares>10.0</shares><date>2024-05-20</date><service>Purchase</service></transaction><transactions><trans><ticker>GOOG</ticker><share>10.0</share><date>2024-05-20</date><service>Sale</service></trans><trans><ticker>GOOG</ticker><share>5.0</share><date>2024-05-20</date><service>Sale</service></trans></transactions></portfolio><portfolio name="test"><stock><ticker>goog</ticker><date>2024-05-20</date><shares>10.0</shares></stock><transaction><service/><ticker>goog</ticker><shares>10.0</shares><date>2024-05-20</date><service>Purchase</service></transaction><transactions><trans><ticker>GOOG</ticker><share>10.0</share><date>2024-05-20</date><service>Sale</service></trans><trans><ticker>GOOG</ticker><share>5.0</share><date>2024-05-20</date><service>Sale</service></trans></transactions></portfolio><portfolio name="test"><stock><ticker>goog</ticker><date>2024-05-20</date><shares>10.0</shares></stock><transaction><service/><ticker>goog</ticker><shares>10.0</shares><date>2024-05-20</date><service>Purchase</service></transaction><transactions><trans><ticker>GOOG</ticker><share>10.0</share><date>2024-05-20</date><service>Sale</service></trans><trans><ticker>GOOG</ticker><share>5.0</share><date>2024-05-20</date><service>Sale</service></trans></transactions></portfolio><stock><ticker>AAPL</ticker><date>2024-06-03</date><shares>50.0</shares></stock><portfolio name="test"><transaction><service/><ticker>GOOG</ticker><shares>10.0</shares><date>2024-05-20</date><service>Purchase</service></transaction><transactions><trans><ticker>GOOG</ticker><share>10.0</share><date>2024-05-20</date><service>Sale</service></trans><trans><ticker>GOOG</ticker><share>5.0</share><date>2024-05-20</date><service>Sale</service></trans></transactions></portfolio><portfolio name="test"><stock><ticker>goog</ticker><date>2024-05-20</date><shares>10.0</shares></stock><transaction><service/><ticker>goog</ticker><shares>10.0</shares><date>2024-05-20</date><service>Purchase</service></transaction><transactions><trans><ticker>GOOG</ticker><share>5.0</share><date>2024-05-20</date><service>Sale</service></trans></transactions></portfolio><portfolio name="test"><stock><ticker>goog</ticker><date>2024-05-20</date><shares>10.0</shares></stock><transaction><service/><ticker>goog</ticker><shares>10.0</shares><date>2024-05-20</date><service>Purchase</service></transaction><transactions><trans><ticker>GOOG</ticker><share>5.0</share><date>2024-05-20</date><service>Sale</service></trans></transactions></portfolio><portfolio name="tet"><stock><ticker>goog</ticker><date>2024-05-20</date><shares>10.0</shares></stock><transaction><service/><ticker>goog</ticker><shares>10.0</shares><date>2024-05-20</date><service>Purchase</service></transaction></portfolio><portfolio name="test"><transaction><service/><ticker>GOOG</ticker><shares>10.0</shares><date>2024-05-20</date><service>Purchase</service></transaction><transactions><trans><ticker>GOOG</ticker><share>5.0</share><date>2024-05-20</date><service>Sale</service></trans></transactions></portfolio><portfolio name="test"><transaction><service/><ticker>GOOG</ticker><shares>10.0</shares><date>2024-05-20</date><service>Purchase</service></transaction><transactions><trans><ticker>GOOG</ticker><share>5.0</share><date>2024-05-20</date><service>Sale</service></trans></transactions></portfolio><portfolio name="test"><transaction><service/><ticker>GOOG</ticker><shares>10.0</shares><date>2024-05-20</date><service>Purchase</service></transaction><transactions><trans><ticker>GOOG</ticker><share>5.0</share><date>2024-05-20</date><service>Sale</service></trans></transactions></portfolio><portfolio name="test"><transaction><service/><ticker>GOOG</ticker><shares>10.0</shares><date>2024-05-20</date><service>Purchase</service></transaction><transactions><trans><ticker>GOOG</ticker><share>5.0</share><date>2024-05-20</date><service>Sale</service></trans></transactions></portfolio><portfolio name="test"><transaction><service/><ticker>GOOG</ticker><shares>10.0</shares><date>2024-05-20</date><service>Purchase</service></transaction><transactions><trans><ticker>GOOG</ticker><share>5.0</share><date>2024-05-20</date><service>Sale</service></trans></transactions></portfolio><portfolio name="test"><stock><ticker>goog</ticker><date>2024-05-20</date><shares>10.0</shares></stock><transaction><service/><ticker>goog</ticker><shares>10.0</shares><date>2024-05-20</date><service>Purchase</service></transaction></portfolio><portfolio name="test"><stock><ticker>GOOG</ticker><date>2024-05-20</date><shares>10.0</shares></stock><transaction><service/><ticker>GOOG</ticker><shares>10.0</shares><date>2024-05-20</date><service>Purchase</service></transaction></portfolio><portfolio name="test"><stock><ticker>goog</ticker><date>2024-05-20</date><shares>10.0</shares></stock><transaction><service/><ticker>goog</ticker><shares>10.0</shares><date>2024-05-20</date><service>Purchase</service></transaction></portfolio></profile>